{
  "main": {
    "id": "9e971c8523b6926e",
    "type": "split",
    "children": [
      {
        "id": "c468565479f10f1d",
        "type": "tabs",
        "children": [
          {
            "id": "b35f5a865361e02f",
            "type": "leaf",
            "state": {
              "type": "markdown",
              "state": {
                "file": "Background/Photogrammetry Concepts.md",
                "mode": "source",
                "source": false
              }
            }
          },
          {
            "id": "0c91220d810a95e6",
            "type": "leaf",
            "state": {
              "type": "markdown",
              "state": {
                "file": "Background/Photogrammetry Concepts.md",
                "mode": "source",
                "source": false
              }
            }
          },
          {
            "id": "881c2b3cf2da753d",
            "type": "leaf",
            "state": {
              "type": "canvas",
              "state": {
                "file": "Questions.canvas",
                "viewState": {
                  "x": 0,
                  "y": 0,
                  "zoom": 0
                }
              }
            }
          }
        ],
        "currentTab": 2
      }
    ],
    "direction": "vertical"
  },
  "left": {
    "id": "a2c6880beadc3131",
    "type": "split",
    "children": [
      {
        "id": "c7324272d0fb6547",
        "type": "tabs",
        "children": [
          {
            "id": "ade0fd5f095dc00e",
            "type": "leaf",
            "state": {
              "type": "file-explorer",
              "state": {
                "sortOrder": "alphabetical"
              }
            }
          },
          {
            "id": "a22e0d3b46a8dbb2",
            "type": "leaf",
            "state": {
              "type": "search",
              "state": {
                "query": "",
                "matchingCase": false,
                "explainSearch": false,
                "collapseAll": false,
                "extraContext": false,
                "sortOrder": "alphabetical"
              }
            }
          },
          {
            "id": "2aa4a65d93843842",
            "type": "leaf",
            "state": {
              "type": "bookmarks",
              "state": {}
            }
          }
        ]
      }
    ],
    "direction": "horizontal",
    "width": 300
  },
  "right": {
    "id": "3331c781f976588c",
    "type": "split",
    "children": [
      {
        "id": "fdc20d8c8b6cc16d",
        "type": "tabs",
        "children": [
          {
            "id": "fa809e431a722e69",
            "type": "leaf",
            "state": {
              "type": "backlink",
              "state": {
                "file": "Questions.canvas",
                "collapseAll": false,
                "extraContext": false,
                "sortOrder": "alphabetical",
                "showSearch": false,
                "searchQuery": "",
                "backlinkCollapsed": false,
                "unlinkedCollapsed": true
              }
            }
          },
          {
            "id": "6ce6bc37686a27b5",
            "type": "leaf",
            "state": {
              "type": "outgoing-link",
              "state": {
                "file": "Questions.canvas",
                "linksCollapsed": false,
                "unlinkedCollapsed": true
              }
            }
          },
          {
            "id": "c9d8eb61b5038e18",
            "type": "leaf",
            "state": {
              "type": "tag",
              "state": {
                "sortOrder": "frequency",
                "useHierarchy": true
              }
            }
          },
          {
            "id": "9c799ce7c9627758",
            "type": "leaf",
            "state": {
              "type": "outline",
              "state": {
                "file": "Questions.canvas"
              }
            }
          }
        ]
      }
    ],
    "direction": "horizontal",
    "width": 300,
    "collapsed": true
  },
  "left-ribbon": {
    "hiddenItems": {
      "switcher:Open quick switcher": false,
      "graph:Open graph view": false,
      "canvas:Create new canvas": false,
      "daily-notes:Open today's daily note": false,
      "templates:Insert template": false,
      "command-palette:Open command palette": false
    }
  },
  "active": "881c2b3cf2da753d",
  "lastOpenFiles": [
    "Solutions and Ideas/Using Voxels.md",
    "Questions.canvas",
    "Papers/lartigueVoxelbasedPathPlanning2014.md",
    "Solutions and Ideas",
    "Papers/lartigueVoxelbasedPathPlanning2014a.md",
    "Media/Papers/lartigueVoxelbasedPathPlanning2014/image-4-x53-y293.png",
    "Background/Photogrammetry Concepts.md",
    "Media/Papers/lartigueVoxelbasedPathPlanning2014",
    "Media/Papers",
    "Methodology/Colmap.md",
    "Background/Glossary.md",
    "Papers/schonbergerStructurefromMotionRevisited2016.md",
    "Untitled.md",
    "lartigueVoxelbasedPathPlanning2014a.md",
    "Templates/Zotero Template DH.md",
    "{{annotation.imageRelativePath}}.md",
    "Templates/Zotero Template.md",
    "pichatSurveyMethods3D2018.md",
    "Untitled 1.canvas",
    "Sprial.md",
    "Methodology/Factors for Preliminary Capture Experiments.md",
    "2023-07-28.md",
    "Papers",
    "lartigueVoxelbasedPathPlanning2014.md",
    "Zotero Template DH.md",
    "Zotero Template.md",
    "Templates",
    "Problem Statement & Objectives/Some Problems.md",
    "Media",
    "Problem Statement & Objectives/Objectives.md",
    "Background/Background Overview.md",
    "Problem Statement & Objectives",
    "Experiments/Spiral vs Circular - 2.md",
    "Experiments/Spiral vs Circular - 1.md",
    "Pasted image 20230726231607.png",
    "Experiments",
    "2023-07-26.md",
    "Background",
    "Methodology/Untitled.canvas",
    "Pasted image 20230725004429.png",
    "Pasted image 20230724230729.png",
    "Pasted image 20230724230036.png",
    "Pasted image 20230724230027.png",
    "Methodology"
  ]
}